{ "class": "go.GraphLinksModel",
  "nodeDataArray": [
    {"key":1, "text":"今天是张三值班维护主机", "name":"核心1", "type":"1", "loc":"500 500"},
    {"key":2, "text":"今天是张三值班维护主机", "name":"核心2", "type":"1", "loc":"550 650"},
    {"key":3, "text":"今天是张三值班维护主机", "name":"防火墙1", "type":"2", "loc":"150 100"},
    {"key":4, "text":"今天是张三值班维护主机", "name":"防火墙2", "type":"2", "loc":"150 150"},
    {"key":5, "text":"今天是张三值班维护主机", "name":"防火墙3", "type":"2", "loc":"200 200"},
    {"key":6, "text":"今天是张三值班维护主机", "name":"防火墙4", "type":"2", "loc":"100 200"},
    {"key":7, "text":"今天是张三值班维护主机", "name":"防火墙5", "type":"2", "loc":"140 130"},
    {"key":8, "text":"今天是张三值班维护主机", "name":"防火墙6", "type":"2", "loc":"230 240"},
    {"key":9, "text":"今天是张三值班维护主机", "name":"服务器1", "type":"3", "loc":"120 160"},
    {"key":10, "text":"今天是张三值班维护主机", "name":"服务器2", "type":"3", "loc":"230 330"},
    {"key":11, "text":"今天是张三值班维护主机", "name":"服务器3", "type":"3", "loc":"97.99999999999997 485"},
    {"key":12, "text":"今天是张三值班维护主机", "name":"服务器4", "type":"3", "loc":"250 210"},
    {"key":13, "text":"今天是张三值班维护主机", "name":"服务器5", "type":"3", "loc":"120 190"},
    {"key":14, "text":"今天是张三值班维护主机", "name":"服务器6", "type":"3", "loc":"200 190"},
    {"key":15, "text":"今天是张三值班维护主机", "name":"服务器7", "type":"3", "loc":"320 330"},
    {"key":16, "text":"今天是张三值班维护主机", "name":"交换机1", "type":"1", "loc":"-100.00000000000003 416"},
    {"key":17, "text":"今天是张三值班维护主机", "name":"交换机2", "type":"1", "loc":"220 130"},
    {"key":18, "text":"今天是张三值班维护主机", "name":"交换机3", "type":"1", "loc":"573.9999999999998 186.00000000000009"},
    {"key":19, "text":"今天是张三值班维护主机", "name":"交换机4", "type":"1", "loc":"320 320"},
    {"key":20, "text":"今天是张三值班维护主机", "name":"灾备1", "type":"3", "loc":"410 480"},
    {"key":21, "text":"今天是张三值班维护主机", "name":"灾备2", "type":"3", "loc":"460 590"},
    {"key":22, "text":"今天是张三值班维护主机", "name":"服务器8", "type":"3", "loc":"140 190"},
    {"category":"token", "at":14, "color":"green", "key":-23, "next":5, "frac":0.01},
    {"category":"token", "at":19, "color":"blue", "key":-24, "next":15, "frac":0.01},
    {"category":"token", "at":21, "color":"yellow", "key":-25, "next":20, "frac":0.01},
    {"category":"token", "at":17, "color":"purple", "key":-26, "next":12, "frac":0.01},
    {"category":"token", "at":20, "color":"red", "key":-27, "next":21, "frac":0.01},
    {"category":"token", "at":10, "color":"black", "key":-28, "next":12, "frac":0.01},
    {"category":"token", "at":16, "color":"green", "key":-29, "next":10, "frac":0.01},
    {"category":"token", "at":21, "color":"blue", "key":-30, "next":20, "frac":0.01},
    {"category":"token", "at":21, "color":"yellow", "key":-31, "next":20, "frac":0.01},
    {"category":"token", "at":21, "color":"purple", "key":-32, "next":20, "frac":0.01},
    {"category":"token", "at":12, "color":"red", "key":-33, "next":2, "frac":0.01}
  ],
  "linkDataArray": [
    {"from":1, "to":3, "text":"represent", "color":null},
    {"from":1, "to":4, "text":"is", "color":null},
    {"from":1, "to":5, "text":"is", "color":null},
    {"from":1, "to":6, "text":"is", "color":null},
    {"from":1, "to":7, "text":"includes", "color":null},
    {"from":2, "to":3, "text":"necessary\nfor", "color":null},
    {"from":2, "to":4, "text":"necessary\nfor", "color":null},
    {"from":2, "to":5, "text":"combine\ntoform", "color":null},
    {"from":2, "to":6, "text":"include", "color":null},
    {"from":2, "to":7, "text":"are", "color":null},
    {"from":2, "to":8, "text":"are", "color":null},
    {"from":5, "to":9, "text":"are", "color":null},
    {"from":3, "to":16, "text":"are", "color":null},
    {"from":3, "to":16, "text":"maybe", "color":null},
    {"from":4, "to":17, "text":"in", "color":null},
    {"from":5, "to":18, "text":"in", "color":null},
    {"from":6, "to":19, "text":"begin\nwith", "color":null},
    {"from":11, "to":22, "text":"with", "color":null},
    {"from":16, "to":10, "text":"with", "color":null},
    {"from":17, "to":11, "text":"aids", "color":null},
    {"from":17, "to":12, "text":"show", "color":null},
    {"from":18, "to":13, "text":"begins\nwith", "color":null},
    {"from":18, "to":14, "text":"between", "color":null},
    {"from":19, "to":15, "text":"test", "color":"text"},
    {"from":20, "to":21, "text":"灾备", "color":null},
    {"from":21, "to":20, "text":"灾备", "color":null}
  ]}